{"httpProtocol":"HTTP/1.1","clientAcceptEncoding":"gzip, deflate, br","requestPriority":"","edgeRequestKeepAliveStatus":1,"requestHeaderNames":{},"clientTcpRtt":7,"clientQuicRtt":0,"colo":"BLR","asn":24309,"asOrganization":"Atria Convergence Technologies Pvt. Ltd.,","country":"IN","isEUCountry":false,"city":"Bengaluru","continent":"AS","region":"Karnataka","regionCode":"KA","timezone":"Asia/Kolkata","longitude":"77.59369","latitude":"12.97194","postalCode":"562114","tlsVersion":"TLSv1.3","tlsCipher":"AEAD-AES256-GCM-SHA384","tlsClientRandom":"VoRIXz2zZz82Kx0r/Le4V8CDV4lVpjVbpVYs0nc+Iv8=","tlsClientCiphersSha1":"kXrN3VEKDdzz2cPKTQaKzpxVTxQ=","tlsClientExtensionsSha1":"1eY97BUYYO8vDaTfHQywB1pcNdM=","tlsClientExtensionsSha1Le":"u4wtEMFQBY18l3BzHAvORm+KGRw=","tlsExportedAuthenticator":{"clientHandshake":"cacee0110a1cb0484034018fbaa42d6f65fcc55cee2488007c4a2b3df7484b9b6cf01b9ddf83bd3b3d0010181b26e18f","serverHandshake":"d701201932d3216f9ac2e4694065dcd8cb570a7bc0b2660f2110d978e33dd8238d931d81ca5ccd57c5bd8dff316e18e0","clientFinished":"2e28711b1b9206ef897bcd31eaa02b3b1bb9b65dbd8abeb47c1cdd4e4f00fc824e5ce8d9f509fd1fa2be485c227f88e0","serverFinished":"a1e7d2dd6e76e448e5c3cfb9e85a3882fe00232a1ae00ca5d1c53367b411a857888bbf68ec97a126e766980534d07e76"},"tlsClientHelloLength":"1603","tlsClientAuth":{"certPresented":"0","certVerified":"NONE","certRevoked":"0","certIssuerDN":"","certSubjectDN":"","certIssuerDNRFC2253":"","certSubjectDNRFC2253":"","certIssuerDNLegacy":"","certSubjectDNLegacy":"","certSerial":"","certIssuerSerial":"","certSKI":"","certIssuerSKI":"","certFingerprintSHA1":"","certFingerprintSHA256":"","certNotBefore":"","certNotAfter":"","certRFC9440":"","certRFC9440TooLarge":false,"certChainRFC9440":"","certChainRFC9440TooLarge":false},"verifiedBotCategory":"","edgeL4":{"deliveryRate":563535},"botManagement":{"corporateProxy":false,"verifiedBot":false,"jsDetection":{"passed":false},"staticResource":false,"detectionIds":{},"score":99}}